symphonai/__init__.py
symphonai/__main__.py
symphonai/compose.py
symphonai/docker.py
symphonai/envs/default
symphonai/sympy/setup.py
symphonai/sympy/sym/__init__.py
symphonai/sympy/sym/proto.py
symphonai/template/node.py
symphonai/template/params.env
symphonai-0.2.4.data/scripts/sym
symphonai-0.2.4.dist-info/LICENSE
symphonai-0.2.4.dist-info/METADATA
symphonai-0.2.4.dist-info/WHEEL
symphonai-0.2.4.dist-info/top_level.txt
symphonai-0.2.4.dist-info/RECORD
