Metadata-Version: 2.1
Name: symphonai
Version: 0.2.4
Summary: A tool to build and run docker images together
Author: Sven Schultze
Author-email: schultze.sven@googlemail.com
Classifier: Programming Language :: Python :: 3
Classifier: License :: OSI Approved :: MIT License
Classifier: Operating System :: OS Independent
License-File: LICENSE
Requires-Dist: pyyaml
Requires-Dist: fire
